instancer/__init__.py
instancer/client.py
instancer/models.py
instancer/server.py
instancer/templates/add_program.html
instancer/templates/base.html
instancer/templates/index.html
instancer-1.0.0.dist-info/licenses/LICENSE
instancer-1.0.0.dist-info/METADATA
instancer-1.0.0.dist-info/WHEEL
instancer-1.0.0.dist-info/entry_points.txt
instancer-1.0.0.dist-info/top_level.txt
instancer-1.0.0.dist-info/RECORD
