Metadata-Version: 2.4
Name: instancer
Version: 1.0.0
Summary: 一个用于程序实例控制和管理的Python包
Home-page: https://github.com/yourusername/instancer
Author: Your Name
Author-email: Instancer Team <instancer@example.com>
Maintainer-email: Instancer Team <instancer@example.com>
License: MIT
Project-URL: Homepage, https://github.com/instancer-team/instancer
Project-URL: Documentation, https://github.com/instancer-team/instancer#readme
Project-URL: Repository, https://github.com/instancer-team/instancer.git
Project-URL: Bug Tracker, https://github.com/instancer-team/instancer/issues
Keywords: instance,control,management,process,monitoring
Classifier: Development Status :: 5 - Production/Stable
Classifier: Intended Audience :: Developers
Classifier: License :: OSI Approved :: MIT License
Classifier: Operating System :: OS Independent
Classifier: Programming Language :: Python :: 3
Classifier: Programming Language :: Python :: 3.7
Classifier: Programming Language :: Python :: 3.8
Classifier: Programming Language :: Python :: 3.9
Classifier: Programming Language :: Python :: 3.10
Classifier: Programming Language :: Python :: 3.11
Classifier: Programming Language :: Python :: 3.12
Classifier: Topic :: Software Development :: Libraries :: Python Modules
Classifier: Topic :: System :: Monitoring
Classifier: Topic :: System :: Systems Administration
Requires-Python: >=3.7
License-File: LICENSE
Requires-Dist: requests>=2.25.0
Requires-Dist: flask>=2.0.0
Requires-Dist: flask-sqlalchemy>=2.5.0
Requires-Dist: psutil>=5.8.0
Requires-Dist: click>=8.0.0
Provides-Extra: dev
Requires-Dist: pytest>=6.0; extra == "dev"
Requires-Dist: pytest-cov>=2.0; extra == "dev"
Requires-Dist: black>=21.0; extra == "dev"
Requires-Dist: flake8>=3.8; extra == "dev"
Requires-Dist: build>=0.8.0; extra == "dev"
Requires-Dist: twine>=4.0.0; extra == "dev"
Dynamic: author
Dynamic: home-page
Dynamic: license-file
Dynamic: requires-python
